laserpy/__init__.py
laserpy-0.1a0.dist-info/LICENSE
laserpy-0.1a0.dist-info/METADATA
laserpy-0.1a0.dist-info/WHEEL
laserpy-0.1a0.dist-info/top_level.txt
laserpy-0.1a0.dist-info/RECORD
