Metadata-Version: 2.1
Name: laserpy
Version: 0.1a0
Summary: A Language Server Protocol implementation for Python
Home-page: https://github.com/thisfred/laserpy
Author: Eric Casteleijn
Author-email: thisfred@gmail.com
License: Hippocratic Licence 2.1
Keywords: lsp,python,tools
Platform: any
Classifier: Development Status :: 1 - Planning
Classifier: Environment :: Console
Classifier: Intended Audience :: Developers
Classifier: License :: Other/Proprietary License
Classifier: Operating System :: POSIX
Classifier: Programming Language :: Python :: 3 :: Only
Classifier: Topic :: Software Development
Classifier: Typing :: Typed
Requires-Python: >=3.8
Requires-Dist: libcst
Provides-Extra: dev
Requires-Dist: pre-commit ; extra == 'dev'
Requires-Dist: twine ; extra == 'dev'
Requires-Dist: wheel ; extra == 'dev'
Provides-Extra: lint
Requires-Dist: pre-commit ; extra == 'lint'
Provides-Extra: test
Requires-Dist: pytest ; extra == 'test'
Requires-Dist: pytest-coverage ; extra == 'test'
